cypd/__init__.py
cypd/_audio.cpython-39-x86_64-linux-gnu.so
cypd/_libpd.cpython-39-x86_64-linux-gnu.so
cypd-0.1.0.dist-info/METADATA
cypd-0.1.0.dist-info/WHEEL
cypd-0.1.0.dist-info/RECORD
cypd-0.1.0.dist-info/licenses/LICENSE
