Metadata-Version: 2.4
Name: cypd
Version: 0.1.0
Summary: A Cython wrapper for libpd (Pure Data) with built-in audio support
Keywords: pure-data,libpd,audio,dsp,synthesis,music,cython,miniaudio
Author-Email: Shakeeb Alireza <shakfu@users.noreply.github.com>
License-Expression: GPL-3.0-or-later
Classifier: Development Status :: 3 - Alpha
Classifier: Intended Audience :: Developers
Classifier: Intended Audience :: Science/Research
Classifier: Operating System :: MacOS
Classifier: Operating System :: POSIX :: Linux
Classifier: Programming Language :: Cython
Classifier: Programming Language :: Python :: 3
Classifier: Programming Language :: Python :: 3.10
Classifier: Programming Language :: Python :: 3.11
Classifier: Programming Language :: Python :: 3.12
Classifier: Programming Language :: Python :: 3.13
Classifier: Programming Language :: Python :: 3.14
Classifier: Topic :: Multimedia :: Sound/Audio
Classifier: Topic :: Multimedia :: Sound/Audio :: Sound Synthesis
Classifier: Topic :: Scientific/Engineering
Project-URL: Homepage, https://github.com/shakfu/cypd
Project-URL: Repository, https://github.com/shakfu/cypd
Project-URL: Issues, https://github.com/shakfu/cypd/issues
Requires-Python: >=3.9
